{
"type": "FeatureCollection",
"name": "obs_199335",
"crs": { "type": "name", "properties": { "name": "urn:ogc:def:crs:OGC:1.3:CRS84" } },
"features": [
{ "type": "Feature", "properties": { "observateur": "Grosso Eric", "date": "2016-04-08T00:00:00Z", "code_ref": 199335.0, "stade_vie": "Inconnu", "url_obs": "https://geonature.arb-idf.fr/geonature/#/synthese/occurrence/859894", "CLASSE": "Aves", "ORDRE": "Phoenicopteriformes", "FAMILLE": "Phoenicopteridae", "ESPECE": "Phoenicopterus roseus" }, "geometry": { "type": "Point", "coordinates": [ 2.006495, 48.956861 ] } },
{ "type": "Feature", "properties": { "observateur": "ALBERTI Ornella, DESPRES Céline", "date": "2022-06-03T00:00:00Z", "code_ref": 199335.0, "stade_vie": "Inconnu", "url_obs": "https://geonature.arb-idf.fr/geonature/#/synthese/occurrence/2269773", "CLASSE": "Aves", "ORDRE": "Phoenicopteriformes", "FAMILLE": "Phoenicopteridae", "ESPECE": "Phoenicopterus roseus" }, "geometry": { "type": "Point", "coordinates": [ 2.28678703308106, 48.622449039445002 ] } },
{ "type": "Feature", "properties": { "observateur": "BAUDOIN Gérard", "date": "2016-04-05T00:00:00Z", "code_ref": 199335.0, "stade_vie": "Inconnu", "url_obs": "https://geonature.arb-idf.fr/geonature/#/synthese/occurrence/1282096", "CLASSE": "Aves", "ORDRE": "Phoenicopteriformes", "FAMILLE": "Phoenicopteridae", "ESPECE": "Phoenicopterus roseus" }, "geometry": { "type": "Point", "coordinates": [ 2.004297, 48.951087 ] } },
{ "type": "Feature", "properties": { "observateur": "Grosso Eric", "date": "2016-03-27T00:00:00Z", "code_ref": 199335.0, "stade_vie": "Inconnu", "url_obs": "https://geonature.arb-idf.fr/geonature/#/synthese/occurrence/859644", "CLASSE": "Aves", "ORDRE": "Phoenicopteriformes", "FAMILLE": "Phoenicopteridae", "ESPECE": "Phoenicopterus roseus" }, "geometry": { "type": "Point", "coordinates": [ 2.006674, 48.956044 ] } },
{ "type": "Feature", "properties": { "observateur": "Piolain Julien", "date": "2016-04-03T00:00:00Z", "code_ref": 199335.0, "stade_vie": "Inconnu", "url_obs": "https://geonature.arb-idf.fr/geonature/#/synthese/occurrence/388454", "CLASSE": "Aves", "ORDRE": "Phoenicopteriformes", "FAMILLE": "Phoenicopteridae", "ESPECE": "Phoenicopterus roseus" }, "geometry": { "type": "Point", "coordinates": [ 2.007365, 48.953298 ] } },
{ "type": "Feature", "properties": { "observateur": "BAUDOIN Gérard", "date": "2001-08-16T00:00:00Z", "code_ref": 199335.0, "stade_vie": "Inconnu", "url_obs": "https://geonature.arb-idf.fr/geonature/#/synthese/occurrence/1273266", "CLASSE": "Aves", "ORDRE": "Phoenicopteriformes", "FAMILLE": "Phoenicopteridae", "ESPECE": "Phoenicopterus roseus" }, "geometry": { "type": "Point", "coordinates": [ 1.626142, 49.022005 ] } },
{ "type": "Feature", "properties": { "observateur": "Piolain Julien", "date": "2016-04-03T00:00:00Z", "code_ref": 199335.0, "stade_vie": null, "url_obs": "https://openobs.mnhn.fr/redirect/sinp/occurrences/48d81048-c9ec-11e7-b1fe-0050569670db", "CLASSE": "Aves", "ORDRE": "Phoenicopteriformes", "FAMILLE": "Phoenicopteridae", "ESPECE": "Phoenicopterus roseus" }, "geometry": { "type": "Point", "coordinates": [ 2.00736, 48.9533 ] } },
{ "type": "Feature", "properties": { "observateur": "Grosso Eric", "date": "2016-03-27T00:00:00Z", "code_ref": 199335.0, "stade_vie": null, "url_obs": "https://openobs.mnhn.fr/redirect/sinp/occurrences/59f75c86-c9ec-11e7-b1fe-0050569670db", "CLASSE": "Aves", "ORDRE": "Phoenicopteriformes", "FAMILLE": "Phoenicopteridae", "ESPECE": "Phoenicopterus roseus" }, "geometry": { "type": "Point", "coordinates": [ 2.00667, 48.95604 ] } },
{ "type": "Feature", "properties": { "observateur": "Grosso Eric", "date": "2016-04-08T00:00:00Z", "code_ref": 199335.0, "stade_vie": null, "url_obs": "https://openobs.mnhn.fr/redirect/sinp/occurrences/59f8fa49-c9ec-11e7-b1fe-0050569670db", "CLASSE": "Aves", "ORDRE": "Phoenicopteriformes", "FAMILLE": "Phoenicopteridae", "ESPECE": "Phoenicopterus roseus" }, "geometry": { "type": "Point", "coordinates": [ 2.00649, 48.95686 ] } }
]
}
