{
"type": "FeatureCollection",
"name": "obs_199335",
"crs": { "type": "name", "properties": { "name": "urn:ogc:def:crs:OGC:1.3:CRS84" } },
"features": [
{ "type": "Feature", "properties": { "code_ref": 199335.0, "date": "2016-04-08", "label": "Phoenicopterus roseus (199335)<hr>2016-04-08<br>Grosso Eric<br><a href=\"https://geonature.arb-idf.fr/geonature/#/synthese/occurrence/859894\">Lien vers l'observation</a>" }, "geometry": { "type": "Point", "coordinates": [ 2.006495, 48.956861 ] } },
{ "type": "Feature", "properties": { "code_ref": 199335.0, "date": "2022-06-03", "label": "Phoenicopterus roseus (199335)<hr>2022-06-03<br>ALBERTI Ornella, DESPRES Céline<br><a href=\"https://geonature.arb-idf.fr/geonature/#/synthese/occurrence/2269773\">Lien vers l'observation</a>" }, "geometry": { "type": "Point", "coordinates": [ 2.28678703308106, 48.622449039445002 ] } },
{ "type": "Feature", "properties": { "code_ref": 199335.0, "date": "2016-04-05", "label": "Phoenicopterus roseus (199335)<hr>2016-04-05<br>BAUDOIN Gérard<br><a href=\"https://geonature.arb-idf.fr/geonature/#/synthese/occurrence/1282096\">Lien vers l'observation</a>" }, "geometry": { "type": "Point", "coordinates": [ 2.004297, 48.951087 ] } },
{ "type": "Feature", "properties": { "code_ref": 199335.0, "date": "2016-03-27", "label": "Phoenicopterus roseus (199335)<hr>2016-03-27<br>Grosso Eric<br><a href=\"https://geonature.arb-idf.fr/geonature/#/synthese/occurrence/859644\">Lien vers l'observation</a>" }, "geometry": { "type": "Point", "coordinates": [ 2.006674, 48.956044 ] } },
{ "type": "Feature", "properties": { "code_ref": 199335.0, "date": "2016-04-03", "label": "Phoenicopterus roseus (199335)<hr>2016-04-03<br>Piolain Julien<br><a href=\"https://geonature.arb-idf.fr/geonature/#/synthese/occurrence/388454\">Lien vers l'observation</a>" }, "geometry": { "type": "Point", "coordinates": [ 2.007365, 48.953298 ] } },
{ "type": "Feature", "properties": { "code_ref": 199335.0, "date": "2001-08-16", "label": "Phoenicopterus roseus (199335)<hr>2001-08-16<br>BAUDOIN Gérard<br><a href=\"https://geonature.arb-idf.fr/geonature/#/synthese/occurrence/1273266\">Lien vers l'observation</a>" }, "geometry": { "type": "Point", "coordinates": [ 1.626142, 49.022005 ] } },
{ "type": "Feature", "properties": { "code_ref": 199335.0, "date": "2016-04-03", "label": "Phoenicopterus roseus (199335)<hr>2016-04-03<br>Piolain Julien<br><a href=\"https://openobs.mnhn.fr/redirect/sinp/occurrences/48d81048-c9ec-11e7-b1fe-0050569670db\">Lien vers l'observation</a>" }, "geometry": { "type": "Point", "coordinates": [ 2.00736, 48.9533 ] } },
{ "type": "Feature", "properties": { "code_ref": 199335.0, "date": "2016-03-27", "label": "Phoenicopterus roseus (199335)<hr>2016-03-27<br>Grosso Eric<br><a href=\"https://openobs.mnhn.fr/redirect/sinp/occurrences/59f75c86-c9ec-11e7-b1fe-0050569670db\">Lien vers l'observation</a>" }, "geometry": { "type": "Point", "coordinates": [ 2.00667, 48.95604 ] } },
{ "type": "Feature", "properties": { "code_ref": 199335.0, "date": "2016-04-08", "label": "Phoenicopterus roseus (199335)<hr>2016-04-08<br>Grosso Eric<br><a href=\"https://openobs.mnhn.fr/redirect/sinp/occurrences/59f8fa49-c9ec-11e7-b1fe-0050569670db\">Lien vers l'observation</a>" }, "geometry": { "type": "Point", "coordinates": [ 2.00649, 48.95686 ] } }
]
}
