{
"type": "FeatureCollection",
"name": "obs_2437",
"crs": { "type": "name", "properties": { "name": "urn:ogc:def:crs:OGC:1.3:CRS84" } },
"features": [
{ "type": "Feature", "properties": { "code_ref": 2437.0, "date": "2017-02-23", "label": "<em>Morus bassanus</em> (Fou de Bassan)<hr>2017-02-23<br>LEBRUN Bruno<br><a href=\"https://geonature.arb-idf.fr/geonature/#/synthese/occurrence/1326155\">Lien vers l'observation</a>" }, "geometry": { "type": "Point", "coordinates": [ 2.170972, 48.740759 ] } },
{ "type": "Feature", "properties": { "code_ref": 2437.0, "date": "2017-02-22", "label": "<em>Morus bassanus</em> (Fou de Bassan)<hr>2017-02-22<br>Brun Joël<br><a href=\"https://geonature.arb-idf.fr/geonature/#/synthese/occurrence/744031\">Lien vers l'observation</a>" }, "geometry": { "type": "Point", "coordinates": [ 2.168359, 48.741833 ] } },
{ "type": "Feature", "properties": { "code_ref": 2437.0, "date": "2017-02-22", "label": "<em>Morus bassanus</em> (Fou de Bassan)<hr>2017-02-22<br>TOURATIER GILLES<br><a href=\"https://geonature.arb-idf.fr/geonature/#/synthese/occurrence/743615\">Lien vers l'observation</a>" }, "geometry": { "type": "Point", "coordinates": [ 2.160666, 48.742193 ] } },
{ "type": "Feature", "properties": { "code_ref": 2437.0, "date": "2017-02-22", "label": "<em>Morus bassanus</em> (Fou de Bassan)<hr>2017-02-22<br>TOURATIER GILLES<br><a href=\"https://openobs.mnhn.fr/redirect/sinp/occurrences/559f0766-c9ec-11e7-b1fe-0050569670db\">Lien vers l'observation</a>" }, "geometry": { "type": "Point", "coordinates": [ 2.16067, 48.74219 ] } },
{ "type": "Feature", "properties": { "code_ref": 2437.0, "date": "2017-02-22", "label": "<em>Morus bassanus</em> (Fou de Bassan)<hr>2017-02-22<br>Brun Joël<br><a href=\"https://openobs.mnhn.fr/redirect/sinp/occurrences/55a2af61-c9ec-11e7-b1fe-0050569670db\">Lien vers l'observation</a>" }, "geometry": { "type": "Point", "coordinates": [ 2.16836, 48.74183 ] } }
]
}
