{
"type": "FeatureCollection",
"name": "obs_3586",
"crs": { "type": "name", "properties": { "name": "urn:ogc:def:crs:OGC:1.3:CRS84" } },
"features": [
{ "type": "Feature", "properties": { "code_ref": 3586.0, "date": "2022-07-16", "label": "<em>Coracias garrulus</em> (Rollier d'Europe)<hr>Marmet Nicolas (2022-07-16)<br><a href=\"https://geonature.arb-idf.fr/geonature/#/synthese/occurrence/2302933\" target=\"_blank\">Lien vers l'observation</a>" }, "geometry": { "type": "Point", "coordinates": [ 3.0192232131958, 48.962264854867293 ] } },
{ "type": "Feature", "properties": { "code_ref": 3586.0, "date": "2022-07-15", "label": "<em>Coracias garrulus</em> (Rollier d'Europe)<hr>Marmet Nicolas (2022-07-15)<br><a href=\"https://geonature.arb-idf.fr/geonature/#/synthese/occurrence/2302960\" target=\"_blank\">Lien vers l'observation</a>" }, "geometry": { "type": "Point", "coordinates": [ 3.018944263458251, 48.963631387868197 ] } },
{ "type": "Feature", "properties": { "code_ref": 3586.0, "date": "2022-07-18", "label": "<em>Coracias garrulus</em> (Rollier d'Europe)<hr>Marmet Nicolas (2022-07-18)<br><a href=\"https://geonature.arb-idf.fr/geonature/#/synthese/occurrence/2302921\" target=\"_blank\">Lien vers l'observation</a>" }, "geometry": { "type": "Point", "coordinates": [ 3.01875114440918, 48.962969257997493 ] } },
{ "type": "Feature", "properties": { "code_ref": 3586.0, "date": "2022-07-17", "label": "<em>Coracias garrulus</em> (Rollier d'Europe)<hr>antoinekita (2022-07-17)<br><a href=\"https://openobs.mnhn.fr/redirect/sinp/occurrences/c7a4f2ae-4db5-4afc-af4f-c1f94201726e\" target=\"_blank\">Lien vers l'observation</a>" }, "geometry": { "type": "Point", "coordinates": [ 3.01948, 48.96424 ] } }
]
}
