{
"type": "FeatureCollection",
"name": "obs_2437",
"crs": { "type": "name", "properties": { "name": "urn:ogc:def:crs:OGC:1.3:CRS84" } },
"features": [
{ "type": "Feature", "properties": { "observateur": "LEBRUN Bruno", "date": "2017-02-23T00:00:00Z", "code_ref": 2437.0, "stade_vie": "Adulte", "url_obs": "https://geonature.arb-idf.fr/geonature/#/synthese/occurrence/1326155", "CLASSE": "Aves", "ORDRE": "Pelecaniformes", "FAMILLE": "Sulidae", "ESPECE": "Morus bassanus" }, "geometry": { "type": "Point", "coordinates": [ 2.170972, 48.740759 ] } },
{ "type": "Feature", "properties": { "observateur": "Brun Joël", "date": "2017-02-22T00:00:00Z", "code_ref": 2437.0, "stade_vie": "Inconnu", "url_obs": "https://geonature.arb-idf.fr/geonature/#/synthese/occurrence/744031", "CLASSE": "Aves", "ORDRE": "Pelecaniformes", "FAMILLE": "Sulidae", "ESPECE": "Morus bassanus" }, "geometry": { "type": "Point", "coordinates": [ 2.168359, 48.741833 ] } },
{ "type": "Feature", "properties": { "observateur": "TOURATIER GILLES", "date": "2017-02-22T00:00:00Z", "code_ref": 2437.0, "stade_vie": "Adulte", "url_obs": "https://geonature.arb-idf.fr/geonature/#/synthese/occurrence/743615", "CLASSE": "Aves", "ORDRE": "Pelecaniformes", "FAMILLE": "Sulidae", "ESPECE": "Morus bassanus" }, "geometry": { "type": "Point", "coordinates": [ 2.160666, 48.742193 ] } },
{ "type": "Feature", "properties": { "observateur": "TOURATIER GILLES", "date": "2017-02-22T00:00:00Z", "code_ref": 2437.0, "stade_vie": null, "url_obs": "https://openobs.mnhn.fr/redirect/sinp/occurrences/559f0766-c9ec-11e7-b1fe-0050569670db", "CLASSE": "Aves", "ORDRE": "Pelecaniformes", "FAMILLE": "Sulidae", "ESPECE": "Morus bassanus" }, "geometry": { "type": "Point", "coordinates": [ 2.16067, 48.74219 ] } },
{ "type": "Feature", "properties": { "observateur": "Brun Joël", "date": "2017-02-22T00:00:00Z", "code_ref": 2437.0, "stade_vie": null, "url_obs": "https://openobs.mnhn.fr/redirect/sinp/occurrences/55a2af61-c9ec-11e7-b1fe-0050569670db", "CLASSE": "Aves", "ORDRE": "Pelecaniformes", "FAMILLE": "Sulidae", "ESPECE": "Morus bassanus" }, "geometry": { "type": "Point", "coordinates": [ 2.16836, 48.74183 ] } }
]
}
