{
"type": "FeatureCollection",
"name": "obs_3586",
"crs": { "type": "name", "properties": { "name": "urn:ogc:def:crs:OGC:1.3:CRS84" } },
"features": [
{ "type": "Feature", "properties": { "code_ref": 3586.0, "date": "2022-07-16", "label": "<em>Coracias garrulus</em> (Rollier d'Europe)<hr>2022-07-16<br>Marmet Nicolas<br><a href=\"https://geonature.arb-idf.fr/geonature/#/synthese/occurrence/2302933\">Lien vers l'observation</a>" }, "geometry": { "type": "Point", "coordinates": [ 3.0192232131958, 48.962264854867293 ] } },
{ "type": "Feature", "properties": { "code_ref": 3586.0, "date": "2022-07-15", "label": "<em>Coracias garrulus</em> (Rollier d'Europe)<hr>2022-07-15<br>Marmet Nicolas<br><a href=\"https://geonature.arb-idf.fr/geonature/#/synthese/occurrence/2302960\">Lien vers l'observation</a>" }, "geometry": { "type": "Point", "coordinates": [ 3.018944263458251, 48.963631387868197 ] } },
{ "type": "Feature", "properties": { "code_ref": 3586.0, "date": "2022-07-18", "label": "<em>Coracias garrulus</em> (Rollier d'Europe)<hr>2022-07-18<br>Marmet Nicolas<br><a href=\"https://geonature.arb-idf.fr/geonature/#/synthese/occurrence/2302921\">Lien vers l'observation</a>" }, "geometry": { "type": "Point", "coordinates": [ 3.01875114440918, 48.962969257997493 ] } },
{ "type": "Feature", "properties": { "code_ref": 3586.0, "date": "2022-07-17", "label": "<em>Coracias garrulus</em> (Rollier d'Europe)<hr>2022-07-17<br>antoinekita<br><a href=\"https://openobs.mnhn.fr/redirect/sinp/occurrences/c7a4f2ae-4db5-4afc-af4f-c1f94201726e\">Lien vers l'observation</a>" }, "geometry": { "type": "Point", "coordinates": [ 3.01948, 48.96424 ] } }
]
}
