{
"type": "FeatureCollection",
"name": "obs_836346",
"crs": { "type": "name", "properties": { "name": "urn:ogc:def:crs:OGC:1.3:CRS84" } },
"features": [
{ "type": "Feature", "properties": { "code_ref": 836346.0, "date": "2012-11-21", "label": "<em>Clanga clanga</em> (Aigle criard)<hr>Non renseigné (2012-11-21)<br><a href=\"https://openobs.mnhn.fr/redirect/sinp/occurrences/304CEA6E-B1C3-0593-E053-2614A8C02206\">Lien vers l'observation</a>" }, "geometry": { "type": "Point", "coordinates": [ 2.35969, 48.83954 ] } },
{ "type": "Feature", "properties": { "code_ref": 836346.0, "date": "2013-08-26", "label": "<em>Clanga clanga</em> (Aigle criard)<hr>Non renseigné (2013-08-26)<br><a href=\"https://openobs.mnhn.fr/redirect/sinp/occurrences/633e96db-35b2-4216-93f7-9f7f57523be0\">Lien vers l'observation</a>" }, "geometry": { "type": "Point", "coordinates": [ 2.61383, 48.67233 ] } },
{ "type": "Feature", "properties": { "code_ref": 836346.0, "date": "2019-10-24", "label": "<em>Clanga clanga</em> (Aigle criard)<hr>ag412 (2019-10-24)<br><a href=\"https://openobs.mnhn.fr/redirect/sinp/occurrences/901fd7d6-965c-4d25-8d0b-84ccbdf99b0a\">Lien vers l'observation</a>" }, "geometry": { "type": "Point", "coordinates": [ 3.40365, 48.40848 ] } },
{ "type": "Feature", "properties": { "code_ref": 836346.0, "date": "2010-10-10", "label": "<em>Clanga clanga</em> (Aigle criard)<hr>Non renseigné (2010-10-10)<br><a href=\"https://openobs.mnhn.fr/redirect/sinp/occurrences/daff8d70-c1e9-4bab-aed6-2ecf1daf8934\">Lien vers l'observation</a>" }, "geometry": { "type": "Point", "coordinates": [ 3.22917, 48.59767 ] } }
]
}
